{"name":"Playwright Report","logo":null,"date":1776751110765,"dateH":"4/21/2026, 1:58:30 PM","duration":172813,"durationH":"2m 53s","timezone":-8,"timezoneOffset":0,"locale":null,"cwd":"/Users/jhoana-crisostomo/Documents/playwright_v2","outputFile":"/Users/jhoana-crisostomo/Documents/playwright_v2/playwright-report/monocart/index.html","outputDir":"/Users/jhoana-crisostomo/Documents/playwright_v2/playwright-report/monocart","metadata":{"actualWorkers":1},"system":{"cpu":{"color":"#117DBB","count":10,"model":"Apple M1 Pro","speed":2400},"mem":{"color":"#8B12AE","total":34359738368},"arch":"arm64","platform":"darwin","release":"25.4.0","type":"Darwin","version":"Darwin Kernel Version 25.4.0: Thu Mar 19 19:30:44 PDT 2026; root:xnu-12377.101.15~1/RELEASE_ARM64_T6000","uptime":713560,"hostname":"Jhoana-Crisostomo","pid":5754,"node":"22.16.0","v8":"12.4.254.21-node.26","timestampStart":1776751110765,"ticks":[{"cpu":{"percent":39.12},"mem":{"free":113016832},"timestamp":1776751111767},{"cpu":{"percent":32.8},"mem":{"free":127533056},"timestamp":1776751113770},{"cpu":{"percent":50.3},"mem":{"free":75235328},"timestamp":1776751115772},{"cpu":{"percent":25.3},"mem":{"free":239190016},"timestamp":1776751117776},{"cpu":{"percent":13.53},"mem":{"free":205553664},"timestamp":1776751119778},{"cpu":{"percent":18.46},"mem":{"free":174555136},"timestamp":1776751121780},{"cpu":{"percent":16.08},"mem":{"free":143147008},"timestamp":1776751123782},{"cpu":{"percent":25.4},"mem":{"free":96354304},"timestamp":1776751125782},{"cpu":{"percent":19.7},"mem":{"free":51216384},"timestamp":1776751127785},{"cpu":{"percent":21.76},"mem":{"free":125173760},"timestamp":1776751129787},{"cpu":{"percent":32.53},"mem":{"free":123764736},"timestamp":1776751131789},{"cpu":{"percent":27.86},"mem":{"free":148258816},"timestamp":1776751133791},{"cpu":{"percent":37.34},"mem":{"free":87474176},"timestamp":1776751135793},{"cpu":{"percent":68.71},"mem":{"free":68222976},"timestamp":1776751137796},{"cpu":{"percent":30.91},"mem":{"free":134774784},"timestamp":1776751139799},{"cpu":{"percent":56.47},"mem":{"free":144130048},"timestamp":1776751141805},{"cpu":{"percent":37.09},"mem":{"free":108199936},"timestamp":1776751143809},{"cpu":{"percent":44.63},"mem":{"free":147849216},"timestamp":1776751145813},{"cpu":{"percent":60.62},"mem":{"free":156188672},"timestamp":1776751147815},{"cpu":{"percent":50.25},"mem":{"free":168542208},"timestamp":1776751149817},{"cpu":{"percent":36.02},"mem":{"free":80461824},"timestamp":1776751151819},{"cpu":{"percent":61.44},"mem":{"free":106037248},"timestamp":1776751153821},{"cpu":{"percent":61.16},"mem":{"free":94158848},"timestamp":1776751155827},{"cpu":{"percent":42.61},"mem":{"free":124043264},"timestamp":1776751157830},{"cpu":{"percent":29.22},"mem":{"free":104202240},"timestamp":1776751159833},{"cpu":{"percent":34.74},"mem":{"free":87736320},"timestamp":1776751161835},{"cpu":{"percent":30.89},"mem":{"free":111165440},"timestamp":1776751163838},{"cpu":{"percent":34.34},"mem":{"free":114950144},"timestamp":1776751165840},{"cpu":{"percent":70.45},"mem":{"free":115146752},"timestamp":1776751167843},{"cpu":{"percent":82.46},"mem":{"free":121536512},"timestamp":1776751169845},{"cpu":{"percent":66.87},"mem":{"free":180469760},"timestamp":1776751171848},{"cpu":{"percent":77.89},"mem":{"free":169902080},"timestamp":1776751173850},{"cpu":{"percent":82.98},"mem":{"free":127565824},"timestamp":1776751175852},{"cpu":{"percent":67.2},"mem":{"free":131448832},"timestamp":1776751177853},{"cpu":{"percent":60.74},"mem":{"free":152764416},"timestamp":1776751179866},{"cpu":{"percent":51.11},"mem":{"free":112558080},"timestamp":1776751181868},{"cpu":{"percent":31.64},"mem":{"free":98140160},"timestamp":1776751183870},{"cpu":{"percent":51.25},"mem":{"free":117161984},"timestamp":1776751185876},{"cpu":{"percent":47.54},"mem":{"free":100679680},"timestamp":1776751187879},{"cpu":{"percent":45.21},"mem":{"free":135331840},"timestamp":1776751189882},{"cpu":{"percent":90.17},"mem":{"free":87130112},"timestamp":1776751191885},{"cpu":{"percent":86.67},"mem":{"free":441810944},"timestamp":1776751193910},{"cpu":{"percent":87.21},"mem":{"free":276054016},"timestamp":1776751195913},{"cpu":{"percent":76.8},"mem":{"free":160792576},"timestamp":1776751197915},{"cpu":{"percent":95.41},"mem":{"free":140525568},"timestamp":1776751199917},{"cpu":{"percent":86.81},"mem":{"free":118128640},"timestamp":1776751201920},{"cpu":{"percent":77.99},"mem":{"free":86179840},"timestamp":1776751203929},{"cpu":{"percent":64.06},"mem":{"free":99090432},"timestamp":1776751205932},{"cpu":{"percent":56.27},"mem":{"free":198836224},"timestamp":1776751207934},{"cpu":{"percent":78.45},"mem":{"free":108249088},"timestamp":1776751209937},{"cpu":{"percent":63.48},"mem":{"free":194478080},"timestamp":1776751211962},{"cpu":{"percent":62.15},"mem":{"free":151486464},"timestamp":1776751213968},{"cpu":{"percent":49.3},"mem":{"free":163905536},"timestamp":1776751215970},{"cpu":{"percent":44.71},"mem":{"free":141770752},"timestamp":1776751217971},{"cpu":{"percent":52.36},"mem":{"free":120504320},"timestamp":1776751219973},{"cpu":{"percent":65.76},"mem":{"free":158220288},"timestamp":1776751221975},{"cpu":{"percent":73.08},"mem":{"free":95174656},"timestamp":1776751223977},{"cpu":{"percent":50.15},"mem":{"free":176062464},"timestamp":1776751225980},{"cpu":{"percent":59.98},"mem":{"free":227852288},"timestamp":1776751227982},{"cpu":{"percent":50.7},"mem":{"free":112033792},"timestamp":1776751229984},{"cpu":{"percent":41.65},"mem":{"free":150519808},"timestamp":1776751231987},{"cpu":{"percent":33.6},"mem":{"free":140656640},"timestamp":1776751233997},{"cpu":{"percent":33.4},"mem":{"free":136396800},"timestamp":1776751235999},{"cpu":{"percent":49},"mem":{"free":92127232},"timestamp":1776751238003},{"cpu":{"percent":56.64},"mem":{"free":72761344},"timestamp":1776751240012},{"cpu":{"percent":47.54},"mem":{"free":113295360},"timestamp":1776751242015},{"cpu":{"percent":52.31},"mem":{"free":105054208},"timestamp":1776751244018},{"cpu":{"percent":49.1},"mem":{"free":86933504},"timestamp":1776751246021},{"cpu":{"percent":46.89},"mem":{"free":143474688},"timestamp":1776751248023},{"cpu":{"percent":44.46},"mem":{"free":176652288},"timestamp":1776751250024},{"cpu":{"percent":31.89},"mem":{"free":106266624},"timestamp":1776751252026},{"cpu":{"percent":30.24},"mem":{"free":227721216},"timestamp":1776751254028},{"cpu":{"percent":39.9},"mem":{"free":114475008},"timestamp":1776751256030},{"cpu":{"percent":66.16},"mem":{"free":517685248},"timestamp":1776751258031},{"cpu":{"percent":58.76},"mem":{"free":328368128},"timestamp":1776751260034},{"cpu":{"percent":74.57},"mem":{"free":167280640},"timestamp":1776751262036},{"cpu":{"percent":53.61},"mem":{"free":143228928},"timestamp":1776751264037},{"cpu":{"percent":55.03},"mem":{"free":141639680},"timestamp":1776751266040},{"cpu":{"percent":63.32},"mem":{"free":124207104},"timestamp":1776751268041},{"cpu":{"percent":51.95},"mem":{"free":95158272},"timestamp":1776751270044},{"cpu":{"percent":33.57},"mem":{"free":108707840},"timestamp":1776751272046},{"cpu":{"percent":43.69},"mem":{"free":76152832},"timestamp":1776751274047},{"cpu":{"percent":22.43},"mem":{"free":84230144},"timestamp":1776751276049},{"cpu":{"percent":37.55},"mem":{"free":110247936},"timestamp":1776751278051},{"cpu":{"percent":64.25},"mem":{"free":133660672},"timestamp":1776751280053},{"cpu":{"percent":62.7},"mem":{"free":316391424},"timestamp":1776751282056},{"cpu":{"percent":90.48},"mem":{"free":188858368},"timestamp":1776751283578}],"workers":1,"jobs":[{"caseId":"68cde0679b3cd7fb1615","parallelIndex":0,"workerIndex":0,"timestamp":1776751115062,"duration":80357},{"caseId":"5e0096f5008032887b5f","parallelIndex":-1,"workerIndex":-1,"timestamp":1776751195420,"duration":1},{"caseId":"18da3532ab026c5d066a","parallelIndex":0,"workerIndex":1,"timestamp":1776751198558,"duration":84542}],"cwd":"/Users/jhoana-crisostomo/Documents/playwright_v2","configFile":"playwright.config.js","playwright":"1.59.1","monocart":"2.10.0","testDir":"","outputFile":"playwright-report/monocart/index.html","outputDir":"playwright-report/monocart","timestampEnd":1776751283578},"artifacts":[],"trends":[],"columns":[{"id":"caseType","name":"","width":36,"sortable":false,"align":"center","formatter":"iconCaseType","detailed":false},{"id":"title","name":"Title","searchable":true,"width":350,"maxWidth":1230,"detailed":false},{"id":"type","name":"Type","width":50,"sortable":false,"align":"center","formatter":"iconType","detailed":false},{"id":"duration","name":"Duration","align":"right","sortAsc":false,"formatter":"duration","detailed":false},{"id":"errors","name":"Errors","width":60,"align":"center","comparer":"errors","formatter":"errors","detailed":false},{"id":"logs","name":"Logs","width":60,"align":"center","comparer":"logs","formatter":"logs","detailed":false},{"id":"annotations","name":"Annotations","width":100,"markdown":true,"searchable":true,"comparer":"annotations","formatter":"annotations","detailed":false},{"id":"attachments","name":"Attachments","width":100,"align":"center","formatter":"attachments","detailed":false},{"id":"status","name":"Status","align":"center","detailed":false},{"id":"expectedStatus","name":"Expected","align":"center","detailed":false},{"id":"outcome","name":"Outcome","align":"center","width":85,"detailed":false},{"id":"retry","name":"Retry","align":"center","width":50,"detailed":false},{"id":"location","name":"Location","classMap":"mcr-location","width":200,"maxWidth":1981,"detailed":false}],"rows":[{"id":"6afadc876bf5777c23aa","title":"ebr-symbion","type":"suite","suiteType":"project","caseNum":3,"subs":[{"id":"afb5e1a2d802ed4b8784","title":"tests/ebr/core/payments/payroll-order.spec.js","type":"suite","suiteType":"file","caseNum":3,"subs":[{"id":"68cde0679b3cd7fb1615","title":"Payroll payment - business owner - payid - credit - Mastercard","type":"case","caseType":"failed","ok":false,"outcome":"unexpected","expectedStatus":"passed","location":"utils/ebr/runtime-skip.js:324:14","logs":["📊 Batch file info: au-1Payee.aba, Payments: 6, Total: $43.43\n","🎯 Mocking e-purchases, current-order/items, user-stats, authorised-accounts, and analytics endpoints\n","🔐 JWT response during navigation: 201 https://b2baupvt.test.ewallet.com.au/1.0/jwt\n","✅ Captured user full name from API response: My First Name My Last Name\n","✅ Captured user email from API response: platinum0@test.com\n","✅ Captured membership tier from API response: PLATINUM\n","💰 Previous points balance captured: 1000043\n","\n🔍 Checking for existing uploaded file...\n","ℹ️ \"Uploaded file details\" not found within 10s\n","🔍 \"Uploaded file details\" visible: false\n","\n📤 First test - uploading batch file...\n","ℹ️ No \"New payees detected\" banner found\n","📊 Batch file details: au-1Payee.aba, Payments: 6, Total: $43.43, Description: Electric Mai\n","[After Upload] ⏳ Waiting for verification...\n","[After Upload] ✅ Batch summary detected\n","✅ Batch file \"au-1Payee.aba\" uploaded successfully\n","\n📋 Processing payees from uploaded file...\n","⏩ \"Uploaded file details\" not found, using default Continue flow\n","✅ Clicked Continue button\n","✅ Payment form loaded\n","💰 Previous points balance captured: 1000043\n","ℹ️ /user-businesses 200 response not observed before selecting business, continuing...\n","✅ Selected business: M.A MARTIN & M.B MARTIN - ABN 36 621 991 399\n","\n💳 Processing payment with method: payid - Mastercard + credit\n","📊 Amount captured from payment form: $43.43\n","\n🔍 [Test] Payment data being passed: {\n  \"method\": \"payid\",\n  \"cardBrand\": \"Mastercard\",\n  \"cardLast4\": \"1005\",\n  \"additionalMethod\": \"credit\",\n  \"pointsToRedeem\": null,\n  \"amount\": \"$43.43\",\n  \"totalPayments\": 6,\n  \"description\": \"Electric Mai\"\n}\n","\n🔍 [Test] About to call selectHowToPay...\n","\u001b[31mUnknown payee type: payroll for country: au, skipping payment method validation\n\u001b[39m","⏳ Waiting for GET /payment-methods?orderType AND POST /program-fees responses after PayID selection...\n","✅ Both payment-methods and program-fees APIs confirmed for PayID\n","\n🔍 [selectCardOrBank] Starting card/bank selection\n","🔍 [selectCardOrBank] Method: payid\n","🔍 [selectCardOrBank] Payment options: {\n  \"timing\": \"now\",\n  \"payeeType\": \"payroll\",\n  \"method\": \"payid\",\n  \"additionalMethod\": \"credit\",\n  \"cardBrand\": \"Mastercard\",\n  \"pointsToRedeem\": null,\n  \"flowType\": \"business owner\",\n  \"redeemLabel\": null,\n  \"title\": \"Payroll payment - business owner - payid - credit - Mastercard\",\n  \"cardLast4\": \"1005\",\n  \"amount\": \"$43.43\",\n  \"totalPayments\": 6,\n  \"batchFileName\": \"au-1Payee.aba\",\n  \"description\": \"Electric Mai\"\n}\n","🔍 [selectCardOrBank] Payee type: Payroll\n","🔍 [selectCardOrBank] Entering credit/debit card path\n","🔍 [selectCardOrBank] Card brand: Mastercard → Mastercard\n","🔍 [selectCardOrBank] Card last 4: 1005\n","🔍 [selectCardOrBank] Card display text: Mastercard *1005\n","🔍 [selectCardOrBank] About to open card selector list...\n","🔍 [selectCardOrBank] Searching for card number only: *1005\n"],"timestamps":[1776751115062,1776751195419],"duration":80357,"annotations":[{"type":"slow","location":{"file":"/Users/jhoana-crisostomo/Documents/playwright_v2/tests/ebr/core/payments/payroll-order.spec.js","line":511,"column":10}}],"tags":[],"timeout":500000,"retry":0,"status":"failed","stepNum":42,"stepFailed":4,"stepSubs":true,"subs":[{"id":"iqcygbhs3ze2omzwuatd","title":"Before Hooks","type":"step","stepType":"hook","startTime":"2026-04-21T05:58:35.059Z","annotations":[],"duration":1789,"location":"","subs":[{"id":"p0oil0wjjo45igvca2tz","title":"Fixture \"browser\"","type":"step","stepType":"fixture","startTime":"2026-04-21T05:58:35.064Z","annotations":[],"duration":781,"location":"","subs":[{"id":"1th78teuhorpaffcjenh","title":"Launch browser","type":"step","stepType":"pw:api","startTime":"2026-04-21T05:58:35.065Z","annotations":[],"duration":779,"location":""}]},{"id":"s1l38rjvocntypo155hk","title":"Fixture \"context\"","type":"step","stepType":"fixture","startTime":"2026-04-21T05:58:35.845Z","annotations":[],"duration":657,"location":"","subs":[{"id":"nx8r86a58s3m3q2ibcfx","title":"Create context","type":"step","stepType":"pw:api","startTime":"2026-04-21T05:58:35.851Z","annotations":[],"duration":648,"location":""}]},{"id":"623v8xip7d7q7jbsxwec","title":"Fixture \"page\"","type":"step","stepType":"fixture","startTime":"2026-04-21T05:58:36.503Z","annotations":[],"duration":345,"location":"","subs":[{"id":"0ncdt9nem45q7vy3b7ae","title":"Create page","type":"step","stepType":"pw:api","startTime":"2026-04-21T05:58:36.504Z","annotations":[],"duration":344,"location":""}]}]},{"id":"myld0uz6vsvvjogqjlyw","title":"Wait for event \"response\"","type":"step","stepType":"pw:api","startTime":"2026-04-21T05:58:36.894Z","annotations":[],"duration":18846,"location":"tests/ebr/core/payments/payroll-order.spec.js:557:56"},{"id":"wrz2uuob9wam59glcpls","title":"Navigate to \"/\"","type":"step","stepType":"pw:api","startTime":"2026-04-21T05:58:36.897Z","annotations":[],"duration":1929,"location":"utils/framework/global-jwt-response-logger.js:207:25"},{"id":"0kunoz2gj45vde751pe2","title":"Click getByRole('link', { name: 'Pay your payroll' })","type":"step","stepType":"pw:api","startTime":"2026-04-21T05:58:55.742Z","annotations":[],"duration":46,"location":"tests/ebr/core/payments/payroll-order.spec.js:558:64"},{"id":"whxstfwqzq3anbjmbgtz","title":"Wait for event \"response\"","type":"step","stepType":"pw:api","startTime":"2026-04-21T05:58:55.788Z","annotations":[],"duration":1219,"location":"tests/ebr/core/payments/payroll-order.spec.js:561:16"},{"id":"jqxkxm4nuom1gsolp0n0","title":"Wait for timeout","type":"step","stepType":"pw:api","startTime":"2026-04-21T05:58:57.008Z","annotations":[],"duration":1014,"location":"tests/ebr/core/payments/payroll-order.spec.js:564:16"},{"id":"xenjm0ufzx2smwys2klt","title":"Wait for selector locator('#sidebar-content').getByText('Uploaded file details')","type":"step","stepType":"pw:api","startTime":"2026-04-21T05:58:58.036Z","annotations":[],"duration":10008,"location":"tests/ebr/core/payments/payroll-order.spec.js:586:40","errors":["TimeoutError: locator.waitFor: Timeout 10000ms exceeded.\nCall log:\n\u001b[2m  - waiting for locator('#sidebar-content').getByText('Uploaded file details') to be visible\u001b[22m\n\n\n\u001b[0m \u001b[90m 584 |\u001b[39m\n \u001b[90m 585 |\u001b[39m     \u001b[36mtry\u001b[39m {\n\u001b[31m\u001b[1m>\u001b[22m\u001b[39m\u001b[90m 586 |\u001b[39m       \u001b[36mawait\u001b[39m uploadedFileDetailsLocator\u001b[33m.\u001b[39mwaitFor({ state\u001b[33m:\u001b[39m \u001b[32m'visible'\u001b[39m\u001b[33m,\u001b[39m timeout\u001b[33m:\u001b[39m \u001b[35m10000\u001b[39m })\u001b[33m;\u001b[39m\n \u001b[90m     |\u001b[39m                                        \u001b[31m\u001b[1m^\u001b[22m\u001b[39m\u001b[0m\n\n    at /Users/jhoana-crisostomo/Documents/playwright_v2/tests/ebr/core/payments/payroll-order.spec.js:586:40"],"errorNum":1},{"id":"4arjd8gg1jc6d5qzguh6","title":"Expect \"toBeVisible\" getByRole('banner').filter({ hasText: 'New payees detected' }).locator('div').first()","type":"step","stepType":"expect","startTime":"2026-04-21T05:59:08.048Z","annotations":[],"duration":5017,"location":"tests/ebr/core/payments/payroll-order.spec.js:667:114","errors":["Error: \u001b[2mexpect(\u001b[22m\u001b[31mlocator\u001b[39m\u001b[2m).\u001b[22mtoBeVisible\u001b[2m(\u001b[22m\u001b[2m)\u001b[22m failed\n\nLocator: getByRole('banner').filter({ hasText: 'New payees detected' }).locator('div').first()\nExpected: visible\nTimeout: 5000ms\nError: element(s) not found\n\nCall log:\n\u001b[2m  - Expect \"toBeVisible\" with timeout 5000ms\u001b[22m\n\u001b[2m  - waiting for getByRole('banner').filter({ hasText: 'New payees detected' }).locator('div').first()\u001b[22m\n\n\n\u001b[0m \u001b[90m 665 |\u001b[39m       \u001b[90m// Check if 'New payees detected' banner is visible and handle it\u001b[39m\n \u001b[90m 666 |\u001b[39m       \u001b[36mtry\u001b[39m {\n\u001b[31m\u001b[1m>\u001b[22m\u001b[39m\u001b[90m 667 |\u001b[39m         \u001b[36mawait\u001b[39m expect(page\u001b[33m.\u001b[39mgetByRole(\u001b[32m'banner'\u001b[39m)\u001b[33m.\u001b[39mfilter({ hasText\u001b[33m:\u001b[39m \u001b[32m'New payees detected'\u001b[39m })\u001b[33m.\u001b[39mlocator(\u001b[32m'div'\u001b[39m)\u001b[33m.\u001b[39mfirst())\u001b[33m.\u001b[39mtoBeVisible({ timeout\u001b[33m:\u001b[39m \u001b[35m5000\u001b[39m })\u001b[33m;\u001b[39m\n \u001b[90m     |\u001b[39m                                                                                                                  \u001b[31m\u001b[1m^\u001b[22m\u001b[39m\u001b[0m\n\n    at /Users/jhoana-crisostomo/Documents/playwright_v2/tests/ebr/core/payments/payroll-order.spec.js:667:114"],"errorNum":1},{"id":"m27hzvt0d35aslza68pq","title":"Wait for selector locator('.fixed.inset-0.z-modal')","type":"step","stepType":"pw:api","startTime":"2026-04-21T05:59:13.066Z","annotations":[],"duration":4,"location":"tests/ebr/core/payments/payroll-order.spec.js:682:10"},{"id":"cvjguvrrgnwqu5a75bzp","title":"Wait for event \"filechooser\"","type":"step","stepType":"pw:api","startTime":"2026-04-21T05:59:13.071Z","annotations":[],"duration":17,"location":"tests/ebr/core/payments/payroll-order.spec.js:689:39"},{"id":"myxv7erbd0dexv1va82d","title":"Click getByText('Upload ABA file')","type":"step","stepType":"pw:api","startTime":"2026-04-21T05:59:13.072Z","annotations":[],"duration":15,"location":"tests/ebr/core/payments/payroll-order.spec.js:690:46"},{"id":"od9lck2k90j3z93ur0js","title":"Set input files","type":"step","stepType":"pw:api","startTime":"2026-04-21T05:59:13.093Z","annotations":[],"duration":18,"location":"tests/ebr/core/payments/payroll-order.spec.js:692:7"},{"id":"bdnn8crech1hmqiyce64","title":"Expect \"toContainText\" locator('#app')","type":"step","stepType":"expect","startTime":"2026-04-21T05:59:13.111Z","annotations":[],"duration":5887,"location":"tests/ebr/core/payments/payroll-order.spec.js:183:40"},{"id":"u7ipynygxbpznaz5rqg1","title":"Expect \"toContainText\" locator('#sidebar-content')","type":"step","stepType":"expect","startTime":"2026-04-21T05:59:28.019Z","annotations":[],"duration":4,"location":"tests/ebr/core/payments/payroll-order.spec.js:696:54"},{"id":"ogtauw9ewkbdondqe7pe","title":"Expect \"toBeEnabled\" getByRole('button', { name: 'Continue' })","type":"step","stepType":"expect","startTime":"2026-04-21T05:59:28.027Z","annotations":[],"duration":5,"location":"tests/ebr/core/payments/payroll-order.spec.js:726:38"},{"id":"aqaumg28av3eimy8n9ll","title":"Click getByRole('button', { name: 'Continue' })","type":"step","stepType":"pw:api","startTime":"2026-04-21T05:59:28.032Z","annotations":[],"duration":19,"location":"tests/ebr/core/payments/payroll-order.spec.js:727:30"},{"id":"70jxl9yiz49d4mw9j3bk","title":"Expect \"toContainText\" locator('form')","type":"step","stepType":"expect","startTime":"2026-04-21T05:59:28.052Z","annotations":[],"duration":5872,"location":"tests/ebr/core/payments/payroll-order.spec.js:731:42"},{"id":"hkh7zzd0v4epjkh6uuq0","title":"Wait for event \"response\"","type":"step","stepType":"pw:api","startTime":"2026-04-21T05:59:33.926Z","annotations":[],"duration":2000,"location":"pages/ebr/core/payments/make.js:1066:8","errors":["TimeoutError: page.waitForResponse: Timeout 2000ms exceeded while waiting for event \"response\"\n\n\u001b[0m \u001b[90m 1064 |\u001b[39m   \u001b[36masync\u001b[39m selectPayingFor() {\n \u001b[90m 1065 |\u001b[39m     \u001b[36mawait\u001b[39m \u001b[36mthis\u001b[39m\u001b[33m.\u001b[39mpage\n\u001b[31m\u001b[1m>\u001b[22m\u001b[39m\u001b[90m 1066 |\u001b[39m       \u001b[33m.\u001b[39mwaitForResponse((res) \u001b[33m=>\u001b[39m res\u001b[33m.\u001b[39murl()\u001b[33m.\u001b[39mincludes(\u001b[32m'/user-businesses?orderBy'\u001b[39m) \u001b[33m&&\u001b[39m res\u001b[33m.\u001b[39mrequest()\u001b[33m.\u001b[39mmethod() \u001b[33m===\u001b[39m \u001b[32m'GET'\u001b[39m \u001b[33m&&\u001b[39m res\u001b[33m.\u001b[39mstatus() \u001b[33m===\u001b[39m \u001b[35m200\u001b[39m\u001b[33m,\u001b[39m { timeout\u001b[33m:\u001b[39m \u001b[35m2000\u001b[39m })\n \u001b[90m      |\u001b[39m        \u001b[31m\u001b[1m^\u001b[22m\u001b[39m\u001b[0m\n\n    at PaymentsMakePage.selectPayingFor (/Users/jhoana-crisostomo/Documents/playwright_v2/pages/ebr/core/payments/make.js:1066:8)\n    at /Users/jhoana-crisostomo/Documents/playwright_v2/tests/ebr/core/payments/payroll-order.spec.js:735:30"],"errorNum":1},{"id":"dxapq1o7vtnorqkgqd9p","title":"Click getByPlaceholder('Select business')","type":"step","stepType":"pw:api","startTime":"2026-04-21T05:59:35.927Z","annotations":[],"duration":58,"location":"pages/ebr/core/payments/make.js:1071:57"},{"id":"zb7mcee878k0kujp3ln4","title":"Wait for selector getByRole('option').first()","type":"step","stepType":"pw:api","startTime":"2026-04-21T05:59:35.986Z","annotations":[],"duration":9,"location":"pages/ebr/core/payments/make.js:1076:20"},{"id":"wub8jmmdnt3fznz528sf","title":"Click getByRole('option').first()","type":"step","stepType":"pw:api","startTime":"2026-04-21T05:59:35.995Z","annotations":[],"duration":49,"location":"pages/ebr/core/payments/make.js:1083:18"},{"id":"6e43qotu2keuo7ik3zjr","title":"Wait for timeout","type":"step","stepType":"pw:api","startTime":"2026-04-21T05:59:36.072Z","annotations":[],"duration":2014,"location":"pages/ebr/core/payments/make.js:711:25"},{"id":"0ity4dt1eqf5ekwfxdlv","title":"Click locator('label').filter({ hasText: 'PayID' })","type":"step","stepType":"pw:api","startTime":"2026-04-21T05:59:38.086Z","annotations":[],"duration":40,"location":"pages/ebr/core/payments/make.js:712:32"},{"id":"e6lnnuyjgvggnmthudai","title":"Wait for event \"response\"","type":"step","stepType":"pw:api","startTime":"2026-04-21T05:59:38.127Z","annotations":[],"duration":2103,"location":"pages/ebr/core/payments/make.js:717:23"},{"id":"40gfz69lv87zerde8tl7","title":"Wait for event \"response\"","type":"step","stepType":"pw:api","startTime":"2026-04-21T05:59:38.127Z","annotations":[],"duration":3966,"location":"pages/ebr/core/payments/make.js:718:23"},{"id":"h5816v6ia30twc2ypkd0","title":"Click locator('input.base-select__input:not([placeholder=\"Select payee\"]):not([placeholder=\"Select business\"])')","type":"step","stepType":"pw:api","startTime":"2026-04-21T05:59:42.094Z","annotations":[],"duration":38,"location":"pages/ebr/core/payments/make.js:1481:30"},{"id":"j7gq8fzziw6a7zy5fdhw","title":"Wait for selector locator('.base-select-popup > ul > li').filter({ hasText: '*1005' }).filter({ hasNotText: 'VERIFY ACCOUNT' }).first()","type":"step","stepType":"pw:api","startTime":"2026-04-21T05:59:42.133Z","annotations":[],"duration":10070,"location":"pages/ebr/core/payments/make.js:1495:24","errors":["TimeoutError: locator.waitFor: Timeout 10000ms exceeded.\nCall log:\n\u001b[2m  - waiting for locator('.base-select-popup > ul > li').filter({ hasText: '*1005' }).filter({ hasNotText: 'VERIFY ACCOUNT' }).first() to be visible\u001b[22m\n\n\n\u001b[0m \u001b[90m 1493 |\u001b[39m       console\u001b[33m.\u001b[39mlog(\u001b[32m`🔍 [selectCardOrBank] Searching for card number only: ${cardNumberOnly}`\u001b[39m)\u001b[33m;\u001b[39m\n \u001b[90m 1494 |\u001b[39m       \u001b[36mconst\u001b[39m cardOption \u001b[33m=\u001b[39m \u001b[36mthis\u001b[39m\u001b[33m.\u001b[39mpage\u001b[33m.\u001b[39mlocator(\u001b[32m'.base-select-popup > ul > li'\u001b[39m)\u001b[33m.\u001b[39mfilter({ hasText\u001b[33m:\u001b[39m cardNumberOnly\u001b[33m,\u001b[39m hasNotText\u001b[33m:\u001b[39m \u001b[32m'VERIFY ACCOUNT'\u001b[39m })\u001b[33m.\u001b[39mfirst()\u001b[33m;\u001b[39m\n\u001b[31m\u001b[1m>\u001b[22m\u001b[39m\u001b[90m 1495 |\u001b[39m       \u001b[36mawait\u001b[39m cardOption\u001b[33m.\u001b[39mwaitFor({ state\u001b[33m:\u001b[39m \u001b[32m'visible'\u001b[39m\u001b[33m,\u001b[39m timeout\u001b[33m:\u001b[39m \u001b[35m10000\u001b[39m })\u001b[33m;\u001b[39m\n \u001b[90m      |\u001b[39m                        \u001b[31m\u001b[1m^\u001b[22m\u001b[39m\u001b[0m\n\n    at PaymentsMakePage.selectCardOrBank (/Users/jhoana-crisostomo/Documents/playwright_v2/pages/ebr/core/payments/make.js:1495:24)\n    at PaymentsMakePage.selectHowToPay (/Users/jhoana-crisostomo/Documents/playwright_v2/pages/ebr/core/payments/make.js:725:11)\n    at /Users/jhoana-crisostomo/Documents/playwright_v2/tests/ebr/core/payments/payroll-order.spec.js:784:5"],"errorNum":1},{"id":"fgmwa0h8r40d4f7b1xi4","title":"After Hooks","type":"step","stepType":"hook","startTime":"2026-04-21T05:59:52.204Z","annotations":[],"duration":2008,"location":"","subs":[{"id":"ytuzjxkirhj0bi1es95u","title":"Fixture \"page\"","type":"step","stepType":"fixture","startTime":"2026-04-21T05:59:52.358Z","annotations":[],"duration":0,"location":""},{"id":"5t5er15tmmr5wk20kffk","title":"Fixture \"context\"","type":"step","stepType":"fixture","startTime":"2026-04-21T05:59:52.358Z","annotations":[],"duration":1848,"location":"","subs":[{"id":"7gme5u6gtie6doai01ht","title":"Close context","type":"step","stepType":"pw:api","startTime":"2026-04-21T05:59:54.106Z","annotations":[],"duration":94,"location":""}]},{"id":"1yvr3tn3o2ztw1dw65pj","title":"Fixture \"baseURL\"","type":"step","stepType":"fixture","startTime":"2026-04-21T05:59:54.209Z","annotations":[],"duration":0,"location":"tests/ebr/core/payments/payroll-order.spec.js:23:6"},{"id":"n8id0197lamzi5867z3q","title":"Fixture \"storageState\"","type":"step","stepType":"fixture","startTime":"2026-04-21T05:59:54.210Z","annotations":[],"duration":0,"location":"tests/ebr/core/payments/payroll-order.spec.js:23:6"}]},{"id":"kchlgcfap5grqojlhtsf","title":"Worker Cleanup","type":"step","stepType":"hook","startTime":"2026-04-21T05:59:54.212Z","annotations":[],"duration":131,"location":"","subs":[{"id":"8osngfywf0w8t30yoica","title":"Fixture \"video\"","type":"step","stepType":"fixture","startTime":"2026-04-21T05:59:54.213Z","annotations":[],"duration":0,"location":"tests/ebr/core/payments/payroll-order.spec.js:23:6"},{"id":"bvsay39ex41ba19xq48o","title":"Fixture \"browser\"","type":"step","stepType":"fixture","startTime":"2026-04-21T05:59:54.213Z","annotations":[],"duration":129,"location":""}]}],"attachments":[{"name":"screenshot","path":"attachments/e701b348b698e1965dffdaaa9d02ab10198cca78.png","contentType":"image/png","retry":0,"fileName":"screenshot-e701b348b698e1965dffdaaa9d02ab10198cca78.png"},{"name":"video","path":"attachments/b29444ee68862a77cad4903c3e033bf85234e814.webm","contentType":"video/webm","retry":0,"fileName":"video-b29444ee68862a77cad4903c3e033bf85234e814.webm"},{"name":"error-context","path":"attachments/ddb83cc6ebe38c19b69d9af72e3adcd4ef17bca9.md","contentType":"text/markdown","retry":0,"link":true,"fileName":"error-context-ddb83cc6ebe38c19b69d9af72e3adcd4ef17bca9.md"},{"name":"trace","path":"attachments/e5762b7eb8ff445190bcc1da1aac0f7e638cc9fb.zip","contentType":"application/zip","retry":0,"fileName":"trace-e5762b7eb8ff445190bcc1da1aac0f7e638cc9fb.zip"}],"errorNum":1,"errorId":"j7gq8fzziw6a7zy5fdhw"},{"id":"5e0096f5008032887b5f","title":"Payroll payment - business owner - payid - credit - Amex","type":"case","caseType":"skipped","ok":true,"outcome":"skipped","expectedStatus":"skipped","location":"utils/ebr/runtime-skip.js:322:25","timestamps":[1776751195420,1776751195421],"duration":1,"annotations":[{"type":"skip","location":{"file":"/Users/jhoana-crisostomo/Documents/playwright_v2/utils/ebr/runtime-skip.js","line":322,"column":25}}],"tags":[],"timeout":60000,"retry":0,"status":"skipped","stepNum":0,"stepFailed":0,"stepSubs":false},{"id":"18da3532ab026c5d066a","title":"Payroll payment - business owner - payid - bank","type":"case","caseType":"failed","ok":false,"outcome":"unexpected","expectedStatus":"passed","location":"utils/ebr/runtime-skip.js:324:14","logs":["📊 Batch file info: au-1Payee.aba, Payments: 6, Total: $43.43\n","🎯 Mocking e-purchases, current-order/items, user-stats, authorised-accounts, and analytics endpoints\n","🔐 JWT response during navigation: 201 https://b2baupvt.test.ewallet.com.au/1.0/jwt\n","✅ Captured user full name from API response: My First Name My Last Name\n","✅ Captured user email from API response: platinum0@test.com\n","✅ Captured membership tier from API response: PLATINUM\n","💰 Previous points balance captured: 1000043\n","\n🔍 Checking for existing uploaded file...\n","ℹ️ \"Uploaded file details\" not found within 10s\n","🔍 \"Uploaded file details\" visible: false\n","\n📤 First test - uploading batch file...\n","ℹ️ No \"New payees detected\" banner found\n","📊 Batch file details: au-1Payee.aba, Payments: 6, Total: $43.43, Description: Electric Mai\n","[After Upload] ⏳ Waiting for verification...\n","[After Upload] ✅ Batch summary detected\n","✅ Batch file \"au-1Payee.aba\" uploaded successfully\n","\n📋 Processing payees from uploaded file...\n","⏩ \"Uploaded file details\" not found, using default Continue flow\n","✅ Clicked Continue button\n","✅ Payment form loaded\n","💰 Previous points balance captured: 1000043\n","ℹ️ /user-businesses 200 response not observed before selecting business, continuing...\n","✅ Selected business: M.A MARTIN & M.B MARTIN - ABN 36 621 991 399\n","\n💳 Processing payment with method: payid + bank\n","📊 Amount captured from payment form: $43.43\n","\n🔍 [Test] Payment data being passed: {\n  \"method\": \"payid\",\n  \"cardBrand\": null,\n  \"additionalMethod\": \"bank\",\n  \"pointsToRedeem\": null,\n  \"amount\": \"$43.43\",\n  \"totalPayments\": 6,\n  \"description\": \"Electric Mai\"\n}\n","\n🔍 [Test] About to call selectHowToPay...\n","\u001b[31mUnknown payee type: payroll for country: au, skipping payment method validation\n\u001b[39m","⏳ Waiting for GET /payment-methods?orderType AND POST /program-fees responses after PayID selection...\n","✅ Both payment-methods and program-fees APIs confirmed for PayID\n","\n🔍 [selectCardOrBank] Starting card/bank selection\n","🔍 [selectCardOrBank] Method: payid\n","🔍 [selectCardOrBank] Payment options: {\n  \"timing\": \"now\",\n  \"payeeType\": \"payroll\",\n  \"method\": \"payid\",\n  \"additionalMethod\": \"bank\",\n  \"cardBrand\": null,\n  \"bankAccountNo\": [\n    \"6789\",\n    \"2367\"\n  ],\n  \"pointsToRedeem\": null,\n  \"flowType\": \"business owner\",\n  \"redeemLabel\": null,\n  \"title\": \"Payroll payment - business owner - payid - bank\",\n  \"amount\": \"$43.43\",\n  \"totalPayments\": 6,\n  \"batchFileName\": \"au-1Payee.aba\",\n  \"description\": \"Electric Mai\"\n}\n","🔍 [selectCardOrBank] Payee type: Payroll\n","ℹ️ Bank account candidate '6789' not found, trying next if available.\n","ℹ️ Bank account candidate '2367' not found, trying next if available.\n"],"timestamps":[1776751198558,1776751283100],"duration":84542,"annotations":[{"type":"slow","location":{"file":"/Users/jhoana-crisostomo/Documents/playwright_v2/tests/ebr/core/payments/payroll-order.spec.js","line":511,"column":10}}],"tags":[],"timeout":500000,"errors":["Error: None of the provided bankAccountNo candidates were found: 6789, 2367\n\n\u001b[0m \u001b[90m 1622 |\u001b[39m       }\n \u001b[90m 1623 |\u001b[39m       \u001b[36mif\u001b[39m (\u001b[33m!\u001b[39mbankOption) {\n\u001b[31m\u001b[1m>\u001b[22m\u001b[39m\u001b[90m 1624 |\u001b[39m         \u001b[36mthrow\u001b[39m \u001b[36mnew\u001b[39m \u001b[33mError\u001b[39m(\u001b[32m`None of the provided bankAccountNo candidates were found: ${validCandidates.join(', ')}`\u001b[39m)\u001b[33m;\u001b[39m\n \u001b[90m      |\u001b[39m               \u001b[31m\u001b[1m^\u001b[22m\u001b[39m\u001b[0m\n\n    at PaymentsMakePage.selectCardOrBank (/Users/jhoana-crisostomo/Documents/playwright_v2/pages/ebr/core/payments/make.js:1624:15)\n    at PaymentsMakePage.selectHowToPay (/Users/jhoana-crisostomo/Documents/playwright_v2/pages/ebr/core/payments/make.js:725:11)\n    at /Users/jhoana-crisostomo/Documents/playwright_v2/tests/ebr/core/payments/payroll-order.spec.js:784:5"],"retry":0,"status":"failed","stepNum":43,"stepFailed":5,"stepSubs":true,"subs":[{"id":"3ligw238e1lrqetppqh1","title":"Before Hooks","type":"step","stepType":"hook","startTime":"2026-04-21T05:59:58.559Z","annotations":[],"duration":1775,"location":"","subs":[{"id":"d8ml4zypovoiklf5xxm5","title":"Fixture \"browser\"","type":"step","stepType":"fixture","startTime":"2026-04-21T05:59:58.564Z","annotations":[],"duration":636,"location":"","subs":[{"id":"yc1assdk3giwdrnw5arc","title":"Launch browser","type":"step","stepType":"pw:api","startTime":"2026-04-21T05:59:58.567Z","annotations":[],"duration":633,"location":""}]},{"id":"msqe7c5pxjesez0gpddc","title":"Fixture \"context\"","type":"step","stepType":"fixture","startTime":"2026-04-21T05:59:59.201Z","annotations":[],"duration":874,"location":"","subs":[{"id":"moqkt806013yz0btecg0","title":"Create context","type":"step","stepType":"pw:api","startTime":"2026-04-21T05:59:59.213Z","annotations":[],"duration":852,"location":""}]},{"id":"gf91g3m10ru71xh5n34c","title":"Fixture \"page\"","type":"step","stepType":"fixture","startTime":"2026-04-21T06:00:00.076Z","annotations":[],"duration":258,"location":"","subs":[{"id":"4599ut0stn3e2ghx4xul","title":"Create page","type":"step","stepType":"pw:api","startTime":"2026-04-21T06:00:00.078Z","annotations":[],"duration":256,"location":""}]}]},{"id":"zq8x1f8ngeev5pooi5jw","title":"Wait for event \"response\"","type":"step","stepType":"pw:api","startTime":"2026-04-21T06:00:00.426Z","annotations":[],"duration":20893,"location":"tests/ebr/core/payments/payroll-order.spec.js:557:56"},{"id":"2rnom8sv8mlu3tf62upw","title":"Navigate to \"/\"","type":"step","stepType":"pw:api","startTime":"2026-04-21T06:00:00.429Z","annotations":[],"duration":2491,"location":"utils/framework/global-jwt-response-logger.js:207:25"},{"id":"i76551911zdbvvq4pypx","title":"Click getByRole('link', { name: 'Pay your payroll' })","type":"step","stepType":"pw:api","startTime":"2026-04-21T06:00:21.321Z","annotations":[],"duration":49,"location":"tests/ebr/core/payments/payroll-order.spec.js:558:64"},{"id":"qweia1r0yhlyrxu1cnx9","title":"Wait for event \"response\"","type":"step","stepType":"pw:api","startTime":"2026-04-21T06:00:21.371Z","annotations":[],"duration":1721,"location":"tests/ebr/core/payments/payroll-order.spec.js:561:16"},{"id":"yzxh2aa1jmpg85i5q2en","title":"Wait for timeout","type":"step","stepType":"pw:api","startTime":"2026-04-21T06:00:23.093Z","annotations":[],"duration":1010,"location":"tests/ebr/core/payments/payroll-order.spec.js:564:16"},{"id":"bpsdgnf4qbs7w5851zwp","title":"Wait for selector locator('#sidebar-content').getByText('Uploaded file details')","type":"step","stepType":"pw:api","startTime":"2026-04-21T06:00:24.113Z","annotations":[],"duration":10009,"location":"tests/ebr/core/payments/payroll-order.spec.js:586:40","errors":["TimeoutError: locator.waitFor: Timeout 10000ms exceeded.\nCall log:\n\u001b[2m  - waiting for locator('#sidebar-content').getByText('Uploaded file details') to be visible\u001b[22m\n\n\n\u001b[0m \u001b[90m 584 |\u001b[39m\n \u001b[90m 585 |\u001b[39m     \u001b[36mtry\u001b[39m {\n\u001b[31m\u001b[1m>\u001b[22m\u001b[39m\u001b[90m 586 |\u001b[39m       \u001b[36mawait\u001b[39m uploadedFileDetailsLocator\u001b[33m.\u001b[39mwaitFor({ state\u001b[33m:\u001b[39m \u001b[32m'visible'\u001b[39m\u001b[33m,\u001b[39m timeout\u001b[33m:\u001b[39m \u001b[35m10000\u001b[39m })\u001b[33m;\u001b[39m\n \u001b[90m     |\u001b[39m                                        \u001b[31m\u001b[1m^\u001b[22m\u001b[39m\u001b[0m\n\n    at /Users/jhoana-crisostomo/Documents/playwright_v2/tests/ebr/core/payments/payroll-order.spec.js:586:40"],"errorNum":1},{"id":"qdl79yksekj5pi2rlt3c","title":"Expect \"toBeVisible\" getByRole('banner').filter({ hasText: 'New payees detected' }).locator('div').first()","type":"step","stepType":"expect","startTime":"2026-04-21T06:00:34.124Z","annotations":[],"duration":5009,"location":"tests/ebr/core/payments/payroll-order.spec.js:667:114","errors":["Error: \u001b[2mexpect(\u001b[22m\u001b[31mlocator\u001b[39m\u001b[2m).\u001b[22mtoBeVisible\u001b[2m(\u001b[22m\u001b[2m)\u001b[22m failed\n\nLocator: getByRole('banner').filter({ hasText: 'New payees detected' }).locator('div').first()\nExpected: visible\nTimeout: 5000ms\nError: element(s) not found\n\nCall log:\n\u001b[2m  - Expect \"toBeVisible\" with timeout 5000ms\u001b[22m\n\u001b[2m  - waiting for getByRole('banner').filter({ hasText: 'New payees detected' }).locator('div').first()\u001b[22m\n\n\n\u001b[0m \u001b[90m 665 |\u001b[39m       \u001b[90m// Check if 'New payees detected' banner is visible and handle it\u001b[39m\n \u001b[90m 666 |\u001b[39m       \u001b[36mtry\u001b[39m {\n\u001b[31m\u001b[1m>\u001b[22m\u001b[39m\u001b[90m 667 |\u001b[39m         \u001b[36mawait\u001b[39m expect(page\u001b[33m.\u001b[39mgetByRole(\u001b[32m'banner'\u001b[39m)\u001b[33m.\u001b[39mfilter({ hasText\u001b[33m:\u001b[39m \u001b[32m'New payees detected'\u001b[39m })\u001b[33m.\u001b[39mlocator(\u001b[32m'div'\u001b[39m)\u001b[33m.\u001b[39mfirst())\u001b[33m.\u001b[39mtoBeVisible({ timeout\u001b[33m:\u001b[39m \u001b[35m5000\u001b[39m })\u001b[33m;\u001b[39m\n \u001b[90m     |\u001b[39m                                                                                                                  \u001b[31m\u001b[1m^\u001b[22m\u001b[39m\u001b[0m\n\n    at /Users/jhoana-crisostomo/Documents/playwright_v2/tests/ebr/core/payments/payroll-order.spec.js:667:114"],"errorNum":1},{"id":"izullk4l6mokfd6d3yxd","title":"Wait for selector locator('.fixed.inset-0.z-modal')","type":"step","stepType":"pw:api","startTime":"2026-04-21T06:00:39.133Z","annotations":[],"duration":5,"location":"tests/ebr/core/payments/payroll-order.spec.js:682:10"},{"id":"zp2igoleg8ivgi2pwe2i","title":"Wait for event \"filechooser\"","type":"step","stepType":"pw:api","startTime":"2026-04-21T06:00:39.138Z","annotations":[],"duration":17,"location":"tests/ebr/core/payments/payroll-order.spec.js:689:39"},{"id":"qblh5x1xekpyegr0soia","title":"Click getByText('Upload ABA file')","type":"step","stepType":"pw:api","startTime":"2026-04-21T06:00:39.139Z","annotations":[],"duration":16,"location":"tests/ebr/core/payments/payroll-order.spec.js:690:46"},{"id":"sn38ywmujezxp2ibono4","title":"Set input files","type":"step","stepType":"pw:api","startTime":"2026-04-21T06:00:39.161Z","annotations":[],"duration":23,"location":"tests/ebr/core/payments/payroll-order.spec.js:692:7"},{"id":"uwa5lpzts8mvz7xcgtsl","title":"Expect \"toContainText\" locator('#app')","type":"step","stepType":"expect","startTime":"2026-04-21T06:00:39.185Z","annotations":[],"duration":5874,"location":"tests/ebr/core/payments/payroll-order.spec.js:183:40"},{"id":"akm044al6cc9wozm96qh","title":"Expect \"toContainText\" locator('#sidebar-content')","type":"step","stepType":"expect","startTime":"2026-04-21T06:01:01.579Z","annotations":[],"duration":4,"location":"tests/ebr/core/payments/payroll-order.spec.js:696:54"},{"id":"1ydyum5cpmy5oxihpkp3","title":"Expect \"toBeEnabled\" getByRole('button', { name: 'Continue' })","type":"step","stepType":"expect","startTime":"2026-04-21T06:01:01.587Z","annotations":[],"duration":6,"location":"tests/ebr/core/payments/payroll-order.spec.js:726:38"},{"id":"kj5hwkvkwlkb7bk4hzvy","title":"Click getByRole('button', { name: 'Continue' })","type":"step","stepType":"pw:api","startTime":"2026-04-21T06:01:01.593Z","annotations":[],"duration":41,"location":"tests/ebr/core/payments/payroll-order.spec.js:727:30"},{"id":"dygoblt0rz89v7zrodec","title":"Expect \"toContainText\" locator('form')","type":"step","stepType":"expect","startTime":"2026-04-21T06:01:01.634Z","annotations":[],"duration":4873,"location":"tests/ebr/core/payments/payroll-order.spec.js:731:42"},{"id":"i4mn5rf3xkqa3fboybg7","title":"Wait for event \"response\"","type":"step","stepType":"pw:api","startTime":"2026-04-21T06:01:06.508Z","annotations":[],"duration":2002,"location":"pages/ebr/core/payments/make.js:1066:8","errors":["TimeoutError: page.waitForResponse: Timeout 2000ms exceeded while waiting for event \"response\"\n\n\u001b[0m \u001b[90m 1064 |\u001b[39m   \u001b[36masync\u001b[39m selectPayingFor() {\n \u001b[90m 1065 |\u001b[39m     \u001b[36mawait\u001b[39m \u001b[36mthis\u001b[39m\u001b[33m.\u001b[39mpage\n\u001b[31m\u001b[1m>\u001b[22m\u001b[39m\u001b[90m 1066 |\u001b[39m       \u001b[33m.\u001b[39mwaitForResponse((res) \u001b[33m=>\u001b[39m res\u001b[33m.\u001b[39murl()\u001b[33m.\u001b[39mincludes(\u001b[32m'/user-businesses?orderBy'\u001b[39m) \u001b[33m&&\u001b[39m res\u001b[33m.\u001b[39mrequest()\u001b[33m.\u001b[39mmethod() \u001b[33m===\u001b[39m \u001b[32m'GET'\u001b[39m \u001b[33m&&\u001b[39m res\u001b[33m.\u001b[39mstatus() \u001b[33m===\u001b[39m \u001b[35m200\u001b[39m\u001b[33m,\u001b[39m { timeout\u001b[33m:\u001b[39m \u001b[35m2000\u001b[39m })\n \u001b[90m      |\u001b[39m        \u001b[31m\u001b[1m^\u001b[22m\u001b[39m\u001b[0m\n\n    at PaymentsMakePage.selectPayingFor (/Users/jhoana-crisostomo/Documents/playwright_v2/pages/ebr/core/payments/make.js:1066:8)\n    at /Users/jhoana-crisostomo/Documents/playwright_v2/tests/ebr/core/payments/payroll-order.spec.js:735:30"],"errorNum":1},{"id":"qo65hxljoh9393fw4222","title":"Click getByPlaceholder('Select business')","type":"step","stepType":"pw:api","startTime":"2026-04-21T06:01:08.511Z","annotations":[],"duration":43,"location":"pages/ebr/core/payments/make.js:1071:57"},{"id":"uqbzpo3d8i0uk9seh3q8","title":"Wait for selector getByRole('option').first()","type":"step","stepType":"pw:api","startTime":"2026-04-21T06:01:08.554Z","annotations":[],"duration":34,"location":"pages/ebr/core/payments/make.js:1076:20"},{"id":"7xrn8y1dqqwpv6dlnco0","title":"Click getByRole('option').first()","type":"step","stepType":"pw:api","startTime":"2026-04-21T06:01:08.589Z","annotations":[],"duration":49,"location":"pages/ebr/core/payments/make.js:1083:18"},{"id":"nvdz3tgorva13snrlb59","title":"Wait for timeout","type":"step","stepType":"pw:api","startTime":"2026-04-21T06:01:08.678Z","annotations":[],"duration":2006,"location":"pages/ebr/core/payments/make.js:711:25"},{"id":"977w4kxyzuk49bjrf1za","title":"Click locator('label').filter({ hasText: 'PayID' })","type":"step","stepType":"pw:api","startTime":"2026-04-21T06:01:10.685Z","annotations":[],"duration":34,"location":"pages/ebr/core/payments/make.js:712:32"},{"id":"jlak9eeqpoew9e65qlhh","title":"Wait for event \"response\"","type":"step","stepType":"pw:api","startTime":"2026-04-21T06:01:10.720Z","annotations":[],"duration":2065,"location":"pages/ebr/core/payments/make.js:717:23"},{"id":"j6tjbs1bt854adu0owsn","title":"Wait for event \"response\"","type":"step","stepType":"pw:api","startTime":"2026-04-21T06:01:10.720Z","annotations":[],"duration":3545,"location":"pages/ebr/core/payments/make.js:718:23"},{"id":"qyxtuxjxagu3pmu9eoee","title":"Click locator('input.base-select__input:not([placeholder=\"Select payee\"]):not([placeholder=\"Select business\"])')","type":"step","stepType":"pw:api","startTime":"2026-04-21T06:01:14.267Z","annotations":[],"duration":31,"location":"pages/ebr/core/payments/make.js:1611:30"},{"id":"694mf6oicaimc18t6km9","title":"Wait for selector locator('.base-select-popup > ul > li').filter({ hasText: '6789' }).filter({ hasNotText: 'VERIFY ACCOUNT' }).first()","type":"step","stepType":"pw:api","startTime":"2026-04-21T06:01:14.299Z","annotations":[],"duration":3008,"location":"pages/ebr/core/payments/make.js:1615:24","errors":["TimeoutError: locator.waitFor: Timeout 3000ms exceeded.\nCall log:\n\u001b[2m  - waiting for locator('.base-select-popup > ul > li').filter({ hasText: '6789' }).filter({ hasNotText: 'VERIFY ACCOUNT' }).first() to be visible\u001b[22m\n\n\n\u001b[0m \u001b[90m 1613 |\u001b[39m         \u001b[36mconst\u001b[39m option \u001b[33m=\u001b[39m \u001b[36mthis\u001b[39m\u001b[33m.\u001b[39mpage\u001b[33m.\u001b[39mlocator(\u001b[32m'.base-select-popup > ul > li'\u001b[39m)\u001b[33m.\u001b[39mfilter({ hasText\u001b[33m:\u001b[39m acct\u001b[33m,\u001b[39m hasNotText\u001b[33m:\u001b[39m \u001b[32m'VERIFY ACCOUNT'\u001b[39m })\u001b[33m.\u001b[39mfirst()\u001b[33m;\u001b[39m\n \u001b[90m 1614 |\u001b[39m         \u001b[36mtry\u001b[39m {\n\u001b[31m\u001b[1m>\u001b[22m\u001b[39m\u001b[90m 1615 |\u001b[39m           \u001b[36mawait\u001b[39m option\u001b[33m.\u001b[39mwaitFor({ state\u001b[33m:\u001b[39m \u001b[32m'visible'\u001b[39m\u001b[33m,\u001b[39m timeout\u001b[33m:\u001b[39m \u001b[35m3000\u001b[39m })\u001b[33m;\u001b[39m\n \u001b[90m      |\u001b[39m                        \u001b[31m\u001b[1m^\u001b[22m\u001b[39m\u001b[0m\n\n    at PaymentsMakePage.selectCardOrBank (/Users/jhoana-crisostomo/Documents/playwright_v2/pages/ebr/core/payments/make.js:1615:24)\n    at PaymentsMakePage.selectHowToPay (/Users/jhoana-crisostomo/Documents/playwright_v2/pages/ebr/core/payments/make.js:725:11)\n    at /Users/jhoana-crisostomo/Documents/playwright_v2/tests/ebr/core/payments/payroll-order.spec.js:784:5"],"errorNum":1},{"id":"wdzuwb7x8jjub3i2bvvh","title":"Wait for selector locator('.base-select-popup > ul > li').filter({ hasText: '2367' }).filter({ hasNotText: 'VERIFY ACCOUNT' }).first()","type":"step","stepType":"pw:api","startTime":"2026-04-21T06:01:17.308Z","annotations":[],"duration":3004,"location":"pages/ebr/core/payments/make.js:1615:24","errors":["TimeoutError: locator.waitFor: Timeout 3000ms exceeded.\nCall log:\n\u001b[2m  - waiting for locator('.base-select-popup > ul > li').filter({ hasText: '2367' }).filter({ hasNotText: 'VERIFY ACCOUNT' }).first() to be visible\u001b[22m\n\n\n\u001b[0m \u001b[90m 1613 |\u001b[39m         \u001b[36mconst\u001b[39m option \u001b[33m=\u001b[39m \u001b[36mthis\u001b[39m\u001b[33m.\u001b[39mpage\u001b[33m.\u001b[39mlocator(\u001b[32m'.base-select-popup > ul > li'\u001b[39m)\u001b[33m.\u001b[39mfilter({ hasText\u001b[33m:\u001b[39m acct\u001b[33m,\u001b[39m hasNotText\u001b[33m:\u001b[39m \u001b[32m'VERIFY ACCOUNT'\u001b[39m })\u001b[33m.\u001b[39mfirst()\u001b[33m;\u001b[39m\n \u001b[90m 1614 |\u001b[39m         \u001b[36mtry\u001b[39m {\n\u001b[31m\u001b[1m>\u001b[22m\u001b[39m\u001b[90m 1615 |\u001b[39m           \u001b[36mawait\u001b[39m option\u001b[33m.\u001b[39mwaitFor({ state\u001b[33m:\u001b[39m \u001b[32m'visible'\u001b[39m\u001b[33m,\u001b[39m timeout\u001b[33m:\u001b[39m \u001b[35m3000\u001b[39m })\u001b[33m;\u001b[39m\n \u001b[90m      |\u001b[39m                        \u001b[31m\u001b[1m^\u001b[22m\u001b[39m\u001b[0m\n\n    at PaymentsMakePage.selectCardOrBank (/Users/jhoana-crisostomo/Documents/playwright_v2/pages/ebr/core/payments/make.js:1615:24)\n    at PaymentsMakePage.selectHowToPay (/Users/jhoana-crisostomo/Documents/playwright_v2/pages/ebr/core/payments/make.js:725:11)\n    at /Users/jhoana-crisostomo/Documents/playwright_v2/tests/ebr/core/payments/payroll-order.spec.js:784:5"],"errorNum":1},{"id":"iyhrxolj8simkkm7ykdh","title":"After Hooks","type":"step","stepType":"hook","startTime":"2026-04-21T06:01:20.313Z","annotations":[],"duration":1519,"location":"","subs":[{"id":"juspbc4oe32goj5gm6zf","title":"Fixture \"page\"","type":"step","stepType":"fixture","startTime":"2026-04-21T06:01:20.414Z","annotations":[],"duration":0,"location":""},{"id":"jhzl0jmj37xs2tlprrjs","title":"Fixture \"context\"","type":"step","stepType":"fixture","startTime":"2026-04-21T06:01:20.414Z","annotations":[],"duration":1413,"location":"","subs":[{"id":"465f33o8yu1ktn9bqlej","title":"Close context","type":"step","stepType":"pw:api","startTime":"2026-04-21T06:01:21.749Z","annotations":[],"duration":74,"location":""}]},{"id":"9r4vk5exft0946x2v55h","title":"Fixture \"baseURL\"","type":"step","stepType":"fixture","startTime":"2026-04-21T06:01:21.830Z","annotations":[],"duration":0,"location":"tests/ebr/core/payments/payroll-order.spec.js:23:6"},{"id":"dh0mdm81e9unvgn5y1pe","title":"Fixture \"storageState\"","type":"step","stepType":"fixture","startTime":"2026-04-21T06:01:21.830Z","annotations":[],"duration":1,"location":"tests/ebr/core/payments/payroll-order.spec.js:23:6"}]},{"id":"2pa2wecou980jt1lxyda","title":"Worker Cleanup","type":"step","stepType":"hook","startTime":"2026-04-21T06:01:21.832Z","annotations":[],"duration":110,"location":"","subs":[{"id":"g4dqg3hv5n6g5xr8unm0","title":"Fixture \"video\"","type":"step","stepType":"fixture","startTime":"2026-04-21T06:01:21.833Z","annotations":[],"duration":0,"location":"tests/ebr/core/payments/payroll-order.spec.js:23:6"},{"id":"qssrwzv9eylpgruikqus","title":"Fixture \"browser\"","type":"step","stepType":"fixture","startTime":"2026-04-21T06:01:21.833Z","annotations":[],"duration":108,"location":""}]}],"attachments":[{"name":"screenshot","path":"attachments/48feb37139b9c9a591b01ff37bd5b6b0964e4816.png","contentType":"image/png","retry":0,"fileName":"screenshot-48feb37139b9c9a591b01ff37bd5b6b0964e4816.png"},{"name":"video","path":"attachments/2d1cacf44fb3ed1fb3a45cb6c4ad9cf025bcc578.webm","contentType":"video/webm","retry":0,"fileName":"video-2d1cacf44fb3ed1fb3a45cb6c4ad9cf025bcc578.webm"},{"name":"error-context","path":"attachments/551ada420a4d1dafa54793254c038dbd1b93ad0e.md","contentType":"text/markdown","retry":0,"link":true,"fileName":"error-context-551ada420a4d1dafa54793254c038dbd1b93ad0e.md"},{"name":"trace","path":"attachments/d6d1bbced526c912cfdb1537171d93e8ca053c9b.zip","contentType":"application/zip","retry":0,"fileName":"trace-d6d1bbced526c912cfdb1537171d93e8ca053c9b.zip"}],"errorNum":1}],"location":"tests/ebr/core/payments/payroll-order.spec.js:0:0"}],"metadata":{"tribe":"ebr","provider":"symbion","providerConfig":{"runtime":{"active":true,"env":"qa"},"country":"au","baseURL":{"qa":"https://symbionelite.test.ewallet.com.au/","uat":"https://symbionelite.uat.ewallet.com.au/"},"credentialVariants":{"qa":["platinum","auth1","auth2","auth3","auth4","noauth1","noauth2","noauth3","noauth4","gold","executive","platinum1","platinum2","platinum3"],"uat":["auth1","auth2","auth3","auth4"]},"sessionWorkers":2,"device":"Desktop Chrome","viewport":{"width":1920,"height":1400},"manageAdminProviderSearchTerm":"symbion","programName":"Symbion Elite Rewards","navEnabled":false,"payeeSpecs":{"bank account":{"description":{"maxLength":8},"reference":{"maxLength":8},"methods":{"pba":{"timings":["now"],"enabled":true},"points+pay":{"timings":["now"],"enabled":true},"payId":{"timings":["now"],"enabled":true,"inherits":["credit/debit card","bank"]},"credit/debit card":{"timings":["now","schedule"],"enabled":true,"cardBrand":{"visa":"accepted","mastercard":"accepted","amex":"not_accepted"}},"bank":{"timings":["now","schedule"],"enabled":true}}},"bpay":{"description":{"maxLength":8},"reference":{"hidden":true},"methods":{"pba":{"enabled":false},"points+pay":{"timings":["now"],"enabled":true},"payId":{"hidden":true},"credit/debit card":{"timings":["now","schedule"],"enabled":true,"cardBrand":{"visa":"accepted","mastercard":"accepted","amex":"not_accepted"}},"bank":{"timings":["now","schedule"],"enabled":true}}},"sponsored biller":{"methods":{"pba":{"hidden":true},"points+pay":{"hidden":true},"payId":{"hidden":true},"credit/debit card":{"timings":["now","schedule"],"enabled":true,"cardBrand":{"visa":"accepted","mastercard":"accepted","amex":"accepted"}},"bank":{"timings":["now","schedule"],"enabled":true}}},"batch order":{"methods":{"pba":{"hidden":true},"points+pay":{"enabled":true},"payId":{"enabled":true,"inherits":["credit/debit card","bank"]},"credit/debit card":{"enabled":true,"cardBrand":{"visa":"accepted","mastercard":"accepted","amex":"not_accepted"}},"bank":{"enabled":true}}}}}}}],"formatters":{},"suiteTypes":["project","file","describe","shard"],"caseTypes":["failed","flaky","skipped","passed"],"traceViewerUrl":"https://trace.playwright.dev/?trace={traceUrl}","mermaid":null,"groupOptions":null,"tags":{},"summary":{"tests":{"name":"Tests","value":3,"nav":true,"id":"tests"},"failed":{"name":"Failed","value":2,"color":"#d00","nav":true,"id":"failed","percent":"66.7%"},"flaky":{"name":"Flaky","value":0,"color":"orange","nav":true,"id":"flaky","percent":"0.0%"},"skipped":{"name":"Skipped","value":1,"color":"gray","nav":true,"id":"skipped","percent":"33.3%"},"passed":{"name":"Passed","value":0,"color":"green","nav":true,"id":"passed","percent":"0.0%"},"steps":{"name":"Steps","value":85,"id":"steps"},"suites":{"name":"Suites","value":1,"id":"suites"},"projects":{"name":"Projects","description":"Suite type is project","value":1,"id":"projects"},"files":{"name":"Files","description":"Suite type is file","value":1,"id":"files"},"describes":{"name":"Describes","description":"Suite type is describe","value":0,"id":"describes"},"shards":{"name":"Shards","description":"Suite type is shard (only in shading mode)","value":0,"id":"shards"},"errors":{"name":"Errors","icon":"error","value":10,"id":"errors"},"retries":{"name":"Retries","icon":"retry","value":0,"id":"retries"},"logs":{"name":"Logs","icon":"log","value":76,"id":"logs"},"attachments":{"name":"Attachments","icon":"attachment","value":8,"id":"attachments"},"artifacts":{"name":"Artifacts","value":0}},"pieChart":{"ns":"mcr-pie","width":360,"height":150,"margin":10,"svg":"<svg viewBox=\"0 0 360 150\" width=\"100%\" height=\"100%\" xmlns=\"http://www.w3.org/2000/svg\"><g class=\"mcr-pie-path-failed\"><path d=\"M75,75 L75,10 A65,65 0 1 1 18.6,107.4 z\" fill=\"#d00\" opacity=\"0.8\" /><animateTransform from=\"0,0\" to=\"0,0\" pos=\"8.7,5\" attributeName=\"transform\" type=\"translate\" dur=\"0.2s\" fill=\"freeze\" repeatCount=\"1\" restart=\"always\" /></g><g class=\"mcr-pie-path-flaky\"><path d=\"\" fill=\"orange\" opacity=\"0.8\" /><animateTransform from=\"0,0\" to=\"0,0\" pos=\"-8.7,5\" attributeName=\"transform\" type=\"translate\" dur=\"0.2s\" fill=\"freeze\" repeatCount=\"1\" restart=\"always\" /></g><g class=\"mcr-pie-path-skipped\"><path d=\"M75,75 L18.6,107.4 A65,65 0 0 1 75,10 z\" fill=\"gray\" opacity=\"0.8\" /><animateTransform from=\"0,0\" to=\"0,0\" pos=\"-8.7,-5\" attributeName=\"transform\" type=\"translate\" dur=\"0.2s\" fill=\"freeze\" repeatCount=\"1\" restart=\"always\" /></g><g class=\"mcr-pie-path-passed\"><path d=\"\" fill=\"green\" opacity=\"0.8\" /><animateTransform from=\"0,0\" to=\"0,0\" pos=\"0,-10\" attributeName=\"transform\" type=\"translate\" dur=\"0.2s\" fill=\"freeze\" repeatCount=\"1\" restart=\"always\" /></g><g font-size=\"14px\" font-family=\"Helvetica, Arial, sans-serif\" transform=\"translate(160 20)\"><g class=\"mcr-pie-legend-failed\" transform=\"translate(0 0)\"><circle cx=\"10\" cy=\"12\" r=\"8\" fill=\"#d00\" opacity=\"0.8\" /><text x=\"25\" y=\"12\" alignment-baseline=\"middle\">Failed</text><text x=\"125\" y=\"12\" alignment-baseline=\"middle\" text-anchor=\"end\">2</text><text x=\"190\" y=\"12\" alignment-baseline=\"middle\" text-anchor=\"end\">66.7%</text></g><g class=\"mcr-pie-legend-flaky\" transform=\"translate(0 24)\"><circle cx=\"10\" cy=\"12\" r=\"8\" fill=\"orange\" opacity=\"0.2\" /><text x=\"25\" y=\"12\" alignment-baseline=\"middle\">Flaky</text><text x=\"125\" y=\"12\" alignment-baseline=\"middle\" text-anchor=\"end\">0</text><text x=\"190\" y=\"12\" alignment-baseline=\"middle\" text-anchor=\"end\">0.0%</text></g><g class=\"mcr-pie-legend-skipped\" transform=\"translate(0 48)\"><circle cx=\"10\" cy=\"12\" r=\"8\" fill=\"gray\" opacity=\"0.8\" /><text x=\"25\" y=\"12\" alignment-baseline=\"middle\">Skipped</text><text x=\"125\" y=\"12\" alignment-baseline=\"middle\" text-anchor=\"end\">1</text><text x=\"190\" y=\"12\" alignment-baseline=\"middle\" text-anchor=\"end\">33.3%</text></g><g class=\"mcr-pie-legend-passed\" transform=\"translate(0 72)\"><circle cx=\"10\" cy=\"12\" r=\"8\" fill=\"green\" opacity=\"0.2\" /><text x=\"25\" y=\"12\" alignment-baseline=\"middle\">Passed</text><text x=\"125\" y=\"12\" alignment-baseline=\"middle\" text-anchor=\"end\">0</text><text x=\"190\" y=\"12\" alignment-baseline=\"middle\" text-anchor=\"end\">0.0%</text></g><g class=\"mcr-pie-legend-tests\" transform=\"translate(0 96)\"><text x=\"25\" y=\"12\" alignment-baseline=\"middle\">Total</text><text x=\"125\" y=\"12\" alignment-baseline=\"middle\" text-anchor=\"end\">3</text></g></g></svg>"},"htmlPath":"playwright-report/monocart/index.html"}
